{"status":"done","publicPath":"http://localhost:3000/assets/bundles/","chunks":{"main":[{"name":"main.js","publicPath":"http://localhost:3000/assets/bundles/main.js","path":"C:\\Users\\NS-HYD-05\\jvbh\\healthtracker\\assets\\bundles\\main.js"}]},"error":"ModuleBuildError","message":"Module build failed: SyntaxError: C:/Users/NS-HYD-05/jvbh/healthtracker/assets/js/components/user_input/UserInputs.jsx: Adjacent JSX elements must be wrapped in an enclosing tag (986:30)\n\n  984 |                                 Submit\n  985 |                             </Button>\n> 986 |                               <ToastContainer \n      |                               ^\n  987 |                                 position=\"top-center\"\n  988 |                                 type=\"default\"\n  989 |                                 autoClose={5000}\n"}