{"status":"done","publicPath":"http://localhost:3000/assets/bundles/","chunks":{"main":[{"name":"main.js","publicPath":"http://localhost:3000/assets/bundles/main.js","path":"C:\\Users\\NS-HYD-05\\jvbh\\healthtracker\\assets\\bundles\\main.js"}]},"error":"ModuleBuildError","message":"Module build failed: SyntaxError: C:/Users/NS-HYD-05/jvbh/healthtracker/assets/js/components/user_input/UserInputs.jsx: Unexpected token, expected , (809:53)\n\n  807 |                                 !this.state.editable &&\n  808 |                                 <div className=\"input col-md-8\">                              \n> 809 |                                   <p style={{overflow-x:}}>{this.state.workout_comment}</p>\n      |                                                      ^\n  810 | \n  811 |                                 </div>\n  812 |                               }\n"}