{"status":"done","publicPath":"http://localhost:3000/assets/bundles/","chunks":{"main":[{"name":"main.js","publicPath":"http://localhost:3000/assets/bundles/main.js","path":"/Users/saumyagarg/wkspace/jvbhw/proj/assets/bundles/main.js"},{"name":"0.f26c31eb46bc2883ef02.hot-update.js","publicPath":"http://localhost:3000/assets/bundles/0.f26c31eb46bc2883ef02.hot-update.js","path":"/Users/saumyagarg/wkspace/jvbhw/proj/assets/bundles/0.f26c31eb46bc2883ef02.hot-update.js"}]},"error":"ModuleBuildError","message":"Module build failed: SyntaxError: Invalid left-hand side in arrow function parameters (21:11)\n\n  19 |     var data = {}\n  20 |     var rn = new RegisterNetwork();\n> 21 |     (data, this.onRegisterSuccess) => rn.register(data,this.onRegisterSuccess);\n     |            ^\n  22 |     console.log('sent request');\n  23 |     return false; \n  24 |   }\n"}